{
  "feature": "firma_compat:twig/birch",
  "placement": [
    {
      "type": "minecraft:block_predicate_filter",
      "predicate": {
        "type": "minecraft:matching_block_tag",
        "tag": "minecraft:replaceable"
      }
    },
    {
      "type": "block_predicate_filter",
      "predicate": {
        "type": "tfc:would_survive_with_fluid",
        "state": {
          "Name": "firma_compat:birch_twig",
          "Properties": {
            "fluid": "empty"
          }
        }
      }
    }
  ]
}